prda/__init__.py
prda/graphic.py
prda/iostream.py
prda/ml.py
prda/prep.py
prda/stats.py
prda/utility.py
prda/ml/__init__.py
prda/ml/clusters.py
prda/ml/evaluations.py
prda/ml/neighbors.py
prda-1.2.0.dist-info/LICENSE
prda-1.2.0.dist-info/METADATA
prda-1.2.0.dist-info/WHEEL
prda-1.2.0.dist-info/top_level.txt
prda-1.2.0.dist-info/RECORD
