Metadata-Version: 2.1
Name: prda
Version: 1.2.0
Summary: Prda contains packages for data processing, analysis and visualization. The ultimate goal is to fill the “last mile” between analysts and packages.
Home-page: https://github.com/4AlexMin/prda
Author: Shaojie Min
Author-email: alexmin@cqu.edu.cn
License: MIT License        
Platform: UNKNOWN
Classifier: Development Status :: 3 - Alpha
Classifier: License :: OSI Approved :: MIT License
Classifier: Programming Language :: Python :: 3.8
Classifier: Topic :: Scientific/Engineering :: Artificial Intelligence
License-File: LICENSE
Requires-Dist: scipy
Requires-Dist: scikit-learn
Requires-Dist: pyspark
Requires-Dist: lifelines
Requires-Dist: seaborn
Requires-Dist: pyecharts
Requires-Dist: numpy
Requires-Dist: pandas
